{"name":"As an admin I can not search admin by name without login","id":"search-admin-by-name;as-an-admin-i-can-not-search-admin-by-name-without-login","testSteps":[{"number":1,"description":"Given I set \"valid endpoint\" for search admin by name","duration":31,"startTime":"2023-12-18T02:56:06.285568500+07:00[Asia/Jakarta]","result":"SUCCESS","precondition":false,"level":0,"children":[{"number":2,"description":"I set {String} for search admin by name","duration":0,"startTime":"2023-12-18T02:56:06.317247900+07:00[Asia/Jakarta]","result":"SUCCESS","precondition":false,"level":1}]},{"number":3,"description":"When I send get request to valid search admin by name endpoint without login","duration":109,"startTime":"2023-12-18T02:56:06.332879400+07:00[Asia/Jakarta]","result":"SUCCESS","precondition":false,"level":0,"children":[{"number":4,"description":"I send get request to valid search admin by name endpoint without login","duration":94,"startTime":"2023-12-18T02:56:06.348509300+07:00[Asia/Jakarta]","result":"SUCCESS","precondition":false,"level":1,"children":[{"number":5,"description":"I set {String} for search admin by name","duration":0,"startTime":"2023-12-18T02:56:06.364135900+07:00[Asia/Jakarta]","result":"SUCCESS","precondition":false,"level":2},{"number":6,"description":"GET http://34.128.69.15:8000/admin/search?name\u003dtry","duration":0,"startTime":"2023-12-18T02:56:06.427082400+07:00[Asia/Jakarta]","result":"SUCCESS","restQuery":{"method":"GET","path":"http://34.128.69.15:8000/admin/search?name\u003dtry","content":"","contentType":"null","requestHeaders":"Accept\u003d*/*","requestCookies":"","responseHeaders":"Content-Type: application/json; charset\u003dUTF-8\r\nVary: Origin\r\nDate: Sun, 17 Dec 2023 19:56:05 GMT\r\nContent-Length: 39\r","responseCookies":"\r","responseBody":"{\n    \"message\": \"missing or malformed jwt\"\n}","statusCode":401},"precondition":false,"level":2}]}]},{"number":7,"description":"Then I receive status code 401","duration":15,"startTime":"2023-12-18T02:56:06.442713700+07:00[Asia/Jakarta]","result":"SUCCESS","precondition":false,"level":0,"children":[{"number":8,"description":"I receive status code 401","duration":0,"startTime":"2023-12-18T02:56:06.458342800+07:00[Asia/Jakarta]","result":"SUCCESS","precondition":false,"level":1}]},{"number":9,"description":"And I receive auth error message","duration":31,"startTime":"2023-12-18T02:56:06.458342800+07:00[Asia/Jakarta]","result":"SUCCESS","precondition":false,"level":0,"children":[{"number":10,"description":"I receive auth error message","duration":15,"startTime":"2023-12-18T02:56:06.458342800+07:00[Asia/Jakarta]","result":"SUCCESS","precondition":false,"level":1}]}],"userStory":{"id":"search-admin-by-name","storyName":"Search Admin By Name","displayName":"Search Admin By Name","path":"admin/auth/search-admin-by-name.feature","narrative":"    As an admin\n    I want to search admin by name\n    So I receive that admin detail account","type":"feature","qualifiedTag":{"name":"Auth/Search Admin By Name","type":"feature","displayName":"Auth/Search Admin By Name"}},"featureTag":{"name":"Auth/Search Admin By Name","type":"feature","displayName":"Auth/Search Admin By Name"},"title":"As an admin I can not search admin by name without login","description":"","tags":[{"name":"NegativeCase","type":"tag","displayName":"NegativeCase"},{"name":"Admin","type":"theme","displayName":"Admin"},{"name":"Auth/Search Admin By Name","type":"feature","displayName":"Search Admin By Name"},{"name":"SearchAdmin","type":"tag","displayName":"SearchAdmin"},{"name":"SearchAdminByName","type":"tag","displayName":"SearchAdminByName"},{"name":"Admin/Auth","type":"capability","displayName":"Auth"}],"allTags":[{"name":"NegativeCase","type":"tag","displayName":"NegativeCase"},{"name":"Admin","type":"theme","displayName":"Admin"},{"name":"Auth/Search Admin By Name","type":"feature","displayName":"Search Admin By Name"},{"name":"SearchAdmin","type":"tag","displayName":"SearchAdmin"},{"name":"SearchAdminByName","type":"tag","displayName":"SearchAdminByName"},{"name":"Admin/Auth","type":"capability","displayName":"Auth"}],"startTime":"2023-12-18T02:56:06.269938600+07:00[Asia/Jakarta]","duration":219,"projectKey":"","isManualTestingUpToDate":false,"context":"windows","manual":false,"testSource":"Cucumber","result":"SUCCESS"}