{"name":"As an admin i cannot create news with invalid token","id":"create-news;as-an-admin-i-cannot-create-news-with-invalid-token","testSteps":[{"number":1,"description":"Given I set valid API Endpoint for create news","duration":12,"startTime":"2023-12-21T10:46:45.354336+07:00[Asia/Jakarta]","result":"SUCCESS","precondition":false,"level":0,"children":[{"number":2,"description":"I set valid API Endpoint for create news","duration":2,"startTime":"2023-12-21T10:46:45.362335200+07:00[Asia/Jakarta]","result":"SUCCESS","precondition":false,"level":1}]},{"number":3,"description":"When I send valid request and set valid json data for create news","duration":51,"startTime":"2023-12-21T10:46:45.367342300+07:00[Asia/Jakarta]","result":"SUCCESS","precondition":false,"level":0,"children":[{"number":4,"description":"I send valid request and set valid json data for create news","duration":48,"startTime":"2023-12-21T10:46:45.369338700+07:00[Asia/Jakarta]","result":"SUCCESS","precondition":false,"level":1,"children":[{"number":5,"description":"I set valid API Endpoint for create news","duration":0,"startTime":"2023-12-21T10:46:45.374336200+07:00[Asia/Jakarta]","result":"SUCCESS","precondition":false,"level":2},{"number":6,"description":"POST http://34.128.69.15:8000/admin/news","duration":0,"startTime":"2023-12-21T10:46:45.417342400+07:00[Asia/Jakarta]","result":"SUCCESS","restQuery":{"method":"POST","path":"http://34.128.69.15:8000/admin/news","content":"","contentType":"application/json","requestHeaders":"Accept\u003d*/*\r\n\t\t\t\tContent-Type\u003dapplication/json","requestCookies":"","responseHeaders":"Content-Type: application/json; charset\u003dUTF-8\r\nVary: Origin\r\nDate: Thu, 21 Dec 2023 03:46:38 GMT\r\nContent-Length: 39\r","responseCookies":"\r","responseBody":"{\n    \"message\": \"missing or malformed jwt\"\n}","statusCode":401},"precondition":false,"level":2}]}]},{"number":7,"description":"And I send invalid token for create news","duration":4,"startTime":"2023-12-21T10:46:45.421343800+07:00[Asia/Jakarta]","result":"SUCCESS","precondition":false,"level":0,"children":[{"number":8,"description":"I send invalid token for create news","duration":0,"startTime":"2023-12-21T10:46:45.423342600+07:00[Asia/Jakarta]","result":"SUCCESS","precondition":false,"level":1}]},{"number":9,"description":"Then I receive code 401","duration":10,"startTime":"2023-12-21T10:46:45.428340200+07:00[Asia/Jakarta]","result":"SUCCESS","precondition":false,"level":0,"children":[{"number":10,"description":"I receive code {Int}","duration":1,"startTime":"2023-12-21T10:46:45.435342100+07:00[Asia/Jakarta]","result":"SUCCESS","precondition":false,"level":1}]},{"number":11,"description":"And I receive auth error message1","duration":9,"startTime":"2023-12-21T10:46:45.441340+07:00[Asia/Jakarta]","result":"SUCCESS","precondition":false,"level":0,"children":[{"number":12,"description":"I receive auth error message1","duration":2,"startTime":"2023-12-21T10:46:45.445346900+07:00[Asia/Jakarta]","result":"SUCCESS","precondition":false,"level":1}]}],"userStory":{"id":"create-news","storyName":"Create News","displayName":"Create News","path":"admin/news/CreateNews.feature","narrative":"  As an admin\n  I want to create news\n  So that I can create news","type":"feature","qualifiedTag":{"name":"News/Create News","type":"feature","displayName":"News/Create News"}},"featureTag":{"name":"News/Create News","type":"feature","displayName":"News/Create News"},"title":"As an admin i cannot create news with invalid token","description":"","tags":[{"name":"Admin","type":"theme","displayName":"Admin"},{"name":"Admin","type":"tag","displayName":"Admin"},{"name":"News/Create News","type":"feature","displayName":"Create News"},{"name":"Admin/News","type":"capability","displayName":"News"}],"allTags":[{"name":"Admin","type":"theme","displayName":"Admin"},{"name":"Admin","type":"tag","displayName":"Admin"},{"name":"News/Create News","type":"feature","displayName":"Create News"},{"name":"Admin/News","type":"capability","displayName":"News"}],"startTime":"2023-12-21T10:46:45.342337600+07:00[Asia/Jakarta]","duration":109,"projectKey":"","isManualTestingUpToDate":false,"context":"windows","manual":false,"testSource":"Cucumber","result":"SUCCESS"}